Metadata-Version: 2.1
Name: Bitcoinprice-notifications
Version: 1.0.7
Summary: A Python package to get Bitcoin price.
Home-page: https://github.com/Teja-s-au6/Bitocin-Price-Notification
Author: Teja S
Author-email: tejaspvg@gmail.com
License: MIT
Platform: UNKNOWN
Classifier: License :: OSI Approved :: MIT License
Classifier: Programming Language :: Python :: 3
Classifier: Programming Language :: Python :: 3.7
